odoo10_addon_l10n_it_pos_fiscalcode-10.0.1.0.0.99.dev3-py3.8-nspkg.pth
odoo/addons/l10n_it_pos_fiscalcode/README.rst
odoo/addons/l10n_it_pos_fiscalcode/__init__.py
odoo/addons/l10n_it_pos_fiscalcode/__manifest__.py
odoo/addons/l10n_it_pos_fiscalcode/i18n/l10n_it_pos_fiscalcode.pot
odoo/addons/l10n_it_pos_fiscalcode/readme/CONTRIBUTORS.rst
odoo/addons/l10n_it_pos_fiscalcode/readme/DESCRIPTION.rst
odoo/addons/l10n_it_pos_fiscalcode/static/description/icon.png
odoo/addons/l10n_it_pos_fiscalcode/static/description/index.html
odoo/addons/l10n_it_pos_fiscalcode/static/src/js/models.js
odoo/addons/l10n_it_pos_fiscalcode/static/src/xml/pos.xml
odoo/addons/l10n_it_pos_fiscalcode/views/assets.xml
odoo10_addon_l10n_it_pos_fiscalcode-10.0.1.0.0.99.dev3.dist-info/METADATA
odoo10_addon_l10n_it_pos_fiscalcode-10.0.1.0.0.99.dev3.dist-info/WHEEL
odoo10_addon_l10n_it_pos_fiscalcode-10.0.1.0.0.99.dev3.dist-info/namespace_packages.txt
odoo10_addon_l10n_it_pos_fiscalcode-10.0.1.0.0.99.dev3.dist-info/top_level.txt
odoo10_addon_l10n_it_pos_fiscalcode-10.0.1.0.0.99.dev3.dist-info/RECORD
