Metadata-Version: 2.1
Name: odoo10-addon-l10n-it-pos-fiscalcode
Version: 10.0.1.0.0.99.dev3
Summary: Gestione codice fiscale del cliente all'interno dell'interfaccia del POS
Home-page: https://github.com/OCA/l10n-italy
Author: Odoo Community Association (OCA)
Author-email: support@odoo-community.org
License: AGPL-3
Platform: UNKNOWN
Classifier: Programming Language :: Python
Classifier: Framework :: Odoo
Classifier: Framework :: Odoo :: 10.0
Classifier: License :: OSI Approved :: GNU Affero General Public License v3
Classifier: Development Status :: 4 - Beta
Requires-Python: ~=2.7
Requires-Dist: odoo10-addon-l10n-it-fiscalcode
Requires-Dist: odoo <10.1dev,>=10.0
